{
    "src": "https://res.cloudinary.com/drvpquisg/image/upload/f_auto,q_auto/v1749682779/krzyzownica_czubata_s3kiug.jpg",
    "thumb": "https://res.cloudinary.com/drvpquisg/image/upload/w_100,c_scale,f_auto,q_auto/v1749682779/krzyzownica_czubata_s3kiug.jpg",
    "caption": "Krzyżownica czubata",
    "latina": "Polygala comosa Schkuhr.",
    "family": "krzyżownicowate",
    "flowering": "Maj - Sierpień",
    "months": [5, 6, 7, 8],
    "habitat": "Pospolita na południu PolskiSłoneczne zbocza, murawy kserotermiczne",
    "occurrence": "Słoneczne zbocza, murawy kserotermiczne",
    "protection": "Brak ochrony gatunkowej",
    "description": "Jej nazwa pochodzi od greckiego słowa 'polys' (dużo) i 'gala' (mleko)...",
    "category": "Bobowce",
    "id": 49
  }