{
    "src": "https://res.cloudinary.com/drvpquisg/image/upload/f_auto,q_auto/v1777014471/ziarnoplon_wiosenny_xiaoet.jpg",
    "thumb":"https://res.cloudinary.com/drvpquisg/image/upload/f_auto,q_auto,w_100,c_fit/v1777014471/ziarnoplon_wiosenny_xiaoet.jpg",
    "caption": "Ziarnopłon wiosenny",
    "latina": "(Ficaria verna Huds.)",
    "family": "jaskrowate",
    "flowering": "Marzec-kwiecień",
    "months": [3, 4],
    "habitat": "Geofit wiosenny głównie żyznych siedlisk leśnych Europy i zachodniej Azji, pospolity w Polsce.",
    "occurrence": "Rośnie najczęściej w żyznych lasach liściastych, zwłaszcza w lasach łęgowych i w wilgotnych grądach, unika natomiast lasów na glebach kwaśnych i ubogich, np. kwaśnych buczyn i kwaśnych dąbrów.",
    "protection": "Brak ochrony gatunkowej",
    "description": "Ziarnopłon to geofit, co oznacza, że magazynuje substancje odżywcze w bulwach pod ziemią. Po szybkim przekwitnięciu wiosną, nadziemna część rośliny znika, a bulwy czekają w stanie uśpienia do kolejnego roku.",
    "category": "Jaskrowce",
    "id": "103"

}
